{
  "version": "5",
  "dialect": "mysql",
  "id": "669d1e36-c914-479e-b50a-6ee565c78b27",
  "prevId": "1f098a22-944d-4ec9-aa07-4849cb09fb8c",
  "tables": {
    "contact_submissions": {
      "name": "contact_submissions",
      "columns": {
        "id": {
          "name": "id",
          "type": "int",
          "primaryKey": false,
          "notNull": true,
          "autoincrement": true
        },
        "name": {
          "name": "name",
          "type": "varchar(255)",
          "primaryKey": false,
          "notNull": true,
          "autoincrement": false
        },
        "email": {
          "name": "email",
          "type": "varchar(320)",
          "primaryKey": false,
          "notNull": true,
          "autoincrement": false
        },
        "phone": {
          "name": "phone",
          "type": "varchar(30)",
          "primaryKey": false,
          "notNull": false,
          "autoincrement": false
        },
        "message": {
          "name": "message",
          "type": "text",
          "primaryKey": false,
          "notNull": true,
          "autoincrement": false
        },
        "service": {
          "name": "service",
          "type": "varchar(255)",
          "primaryKey": false,
          "notNull": false,
          "autoincrement": false
        },
        "address": {
          "name": "address",
          "type": "varchar(500)",
          "primaryKey": false,
          "notNull": false,
          "autoincrement": false
        },
        "photoUrl": {
          "name": "photoUrl",
          "type": "varchar(1000)",
          "primaryKey": false,
          "notNull": false,
          "autoincrement": false
        },
        "photoKey": {
          "name": "photoKey",
          "type": "varchar(500)",
          "primaryKey": false,
          "notNull": false,
          "autoincrement": false
        },
        "createdAt": {
          "name": "createdAt",
          "type": "timestamp",
          "primaryKey": false,
          "notNull": true,
          "autoincrement": false,
          "default": "(now())"
        }
      },
      "indexes": {},
      "foreignKeys": {},
      "compositePrimaryKeys": {
        "contact_submissions_id": {
          "name": "contact_submissions_id",
          "columns": [
            "id"
          ]
        }
      },
      "uniqueConstraints": {},
      "checkConstraint": {}
    },
    "reviews": {
      "name": "reviews",
      "columns": {
        "id": {
          "name": "id",
          "type": "int",
          "primaryKey": false,
          "notNull": true,
          "autoincrement": true
        },
        "name": {
          "name": "name",
          "type": "varchar(255)",
          "primaryKey": false,
          "notNull": true,
          "autoincrement": false
        },
        "rating": {
          "name": "rating",
          "type": "int",
          "primaryKey": false,
          "notNull": true,
          "autoincrement": false
        },
        "text": {
          "name": "text",
          "type": "text",
          "primaryKey": false,
          "notNull": true,
          "autoincrement": false
        },
        "service": {
          "name": "service",
          "type": "varchar(255)",
          "primaryKey": false,
          "notNull": false,
          "autoincrement": false
        },
        "isPrePopulated": {
          "name": "isPrePopulated",
          "type": "int",
          "primaryKey": false,
          "notNull": true,
          "autoincrement": false,
          "default": 0
        },
        "createdAt": {
          "name": "createdAt",
          "type": "timestamp",
          "primaryKey": false,
          "notNull": true,
          "autoincrement": false,
          "default": "(now())"
        }
      },
      "indexes": {},
      "foreignKeys": {},
      "compositePrimaryKeys": {
        "reviews_id": {
          "name": "reviews_id",
          "columns": [
            "id"
          ]
        }
      },
      "uniqueConstraints": {},
      "checkConstraint": {}
    },
    "service_categories": {
      "name": "service_categories",
      "columns": {
        "id": {
          "name": "id",
          "type": "int",
          "primaryKey": false,
          "notNull": true,
          "autoincrement": true
        },
        "serviceId": {
          "name": "serviceId",
          "type": "varchar(100)",
          "primaryKey": false,
          "notNull": true,
          "autoincrement": false
        },
        "name": {
          "name": "name",
          "type": "varchar(255)",
          "primaryKey": false,
          "notNull": true,
          "autoincrement": false
        },
        "description": {
          "name": "description",
          "type": "text",
          "primaryKey": false,
          "notNull": false,
          "autoincrement": false
        },
        "image": {
          "name": "image",
          "type": "varchar(1000)",
          "primaryKey": false,
          "notNull": false,
          "autoincrement": false
        },
        "category": {
          "name": "category",
          "type": "enum('construction','plowing')",
          "primaryKey": false,
          "notNull": true,
          "autoincrement": false
        },
        "sortOrder": {
          "name": "sortOrder",
          "type": "int",
          "primaryKey": false,
          "notNull": true,
          "autoincrement": false,
          "default": 0
        },
        "createdAt": {
          "name": "createdAt",
          "type": "timestamp",
          "primaryKey": false,
          "notNull": true,
          "autoincrement": false,
          "default": "(now())"
        }
      },
      "indexes": {},
      "foreignKeys": {},
      "compositePrimaryKeys": {
        "service_categories_id": {
          "name": "service_categories_id",
          "columns": [
            "id"
          ]
        }
      },
      "uniqueConstraints": {
        "service_categories_serviceId_unique": {
          "name": "service_categories_serviceId_unique",
          "columns": [
            "serviceId"
          ]
        }
      },
      "checkConstraint": {}
    },
    "service_images": {
      "name": "service_images",
      "columns": {
        "id": {
          "name": "id",
          "type": "int",
          "primaryKey": false,
          "notNull": true,
          "autoincrement": true
        },
        "serviceId": {
          "name": "serviceId",
          "type": "varchar(100)",
          "primaryKey": false,
          "notNull": true,
          "autoincrement": false
        },
        "imageUrl": {
          "name": "imageUrl",
          "type": "varchar(1000)",
          "primaryKey": false,
          "notNull": true,
          "autoincrement": false
        },
        "imageKey": {
          "name": "imageKey",
          "type": "varchar(500)",
          "primaryKey": false,
          "notNull": false,
          "autoincrement": false
        },
        "isPrimary": {
          "name": "isPrimary",
          "type": "int",
          "primaryKey": false,
          "notNull": true,
          "autoincrement": false,
          "default": 0
        },
        "createdAt": {
          "name": "createdAt",
          "type": "timestamp",
          "primaryKey": false,
          "notNull": true,
          "autoincrement": false,
          "default": "(now())"
        }
      },
      "indexes": {},
      "foreignKeys": {},
      "compositePrimaryKeys": {
        "service_images_id": {
          "name": "service_images_id",
          "columns": [
            "id"
          ]
        }
      },
      "uniqueConstraints": {},
      "checkConstraint": {}
    },
    "users": {
      "name": "users",
      "columns": {
        "id": {
          "name": "id",
          "type": "int",
          "primaryKey": false,
          "notNull": true,
          "autoincrement": true
        },
        "openId": {
          "name": "openId",
          "type": "varchar(64)",
          "primaryKey": false,
          "notNull": true,
          "autoincrement": false
        },
        "name": {
          "name": "name",
          "type": "text",
          "primaryKey": false,
          "notNull": false,
          "autoincrement": false
        },
        "email": {
          "name": "email",
          "type": "varchar(320)",
          "primaryKey": false,
          "notNull": false,
          "autoincrement": false
        },
        "loginMethod": {
          "name": "loginMethod",
          "type": "varchar(64)",
          "primaryKey": false,
          "notNull": false,
          "autoincrement": false
        },
        "role": {
          "name": "role",
          "type": "enum('user','admin')",
          "primaryKey": false,
          "notNull": true,
          "autoincrement": false,
          "default": "'user'"
        },
        "createdAt": {
          "name": "createdAt",
          "type": "timestamp",
          "primaryKey": false,
          "notNull": true,
          "autoincrement": false,
          "default": "(now())"
        },
        "updatedAt": {
          "name": "updatedAt",
          "type": "timestamp",
          "primaryKey": false,
          "notNull": true,
          "autoincrement": false,
          "onUpdate": true,
          "default": "(now())"
        },
        "lastSignedIn": {
          "name": "lastSignedIn",
          "type": "timestamp",
          "primaryKey": false,
          "notNull": true,
          "autoincrement": false,
          "default": "(now())"
        }
      },
      "indexes": {},
      "foreignKeys": {},
      "compositePrimaryKeys": {
        "users_id": {
          "name": "users_id",
          "columns": [
            "id"
          ]
        }
      },
      "uniqueConstraints": {
        "users_openId_unique": {
          "name": "users_openId_unique",
          "columns": [
            "openId"
          ]
        }
      },
      "checkConstraint": {}
    }
  },
  "views": {},
  "_meta": {
    "schemas": {},
    "tables": {},
    "columns": {}
  },
  "internal": {
    "tables": {},
    "indexes": {}
  }
}